netHighTech/__init__.py
nethightech-1.0.1.dist-info/METADATA
nethightech-1.0.1.dist-info/WHEEL
nethightech-1.0.1.dist-info/top_level.txt
nethightech-1.0.1.dist-info/RECORD
