Metadata-Version: 2.4
Name: netHighTech
Version: 1.0.1
Summary: A package for speech recognition using Selenium and WebDriver
Author: Zubair Khan
Author-email: zubairdev00@gmail.com
Requires-Dist: selenium
Requires-Dist: webdriver-manager
Dynamic: author
Dynamic: author-email
Dynamic: requires-dist
Dynamic: summary
